main.py
jimmy_utils-1.0.1.dist-info/METADATA
jimmy_utils-1.0.1.dist-info/WHEEL
jimmy_utils-1.0.1.dist-info/top_level.txt
jimmy_utils-1.0.1.dist-info/RECORD
